open_flamingo/__init__.py
open_flamingo/eval/__init__.py
open_flamingo/eval/classification_utils.py
open_flamingo/eval/coco_metric.py
open_flamingo/eval/eval_datasets.py
open_flamingo/eval/eval_model.py
open_flamingo/eval/evaluate.py
open_flamingo/eval/ok_vqa_utils.py
open_flamingo/eval/rices.py
open_flamingo/eval/utils.py
open_flamingo/eval/vqa_metric.py
open_flamingo/src/__init__.py
open_flamingo/src/factory.py
open_flamingo/src/flamingo.py
open_flamingo/src/flamingo_lm.py
open_flamingo/src/helpers.py
open_flamingo/src/utils.py
open_flamingo/train/__init__.py
open_flamingo/train/data.py
open_flamingo/train/data_utils.py
open_flamingo/train/distributed.py
open_flamingo/train/train.py
open_flamingo/train/train_utils.py
open_flamingo-2.0.1.data/data/README.md
open_flamingo-2.0.1.dist-info/LICENSE
open_flamingo-2.0.1.dist-info/METADATA
open_flamingo-2.0.1.dist-info/WHEEL
open_flamingo-2.0.1.dist-info/top_level.txt
open_flamingo-2.0.1.dist-info/RECORD
