Metadata-Version: 2.1
Name: open-flamingo
Version: 2.0.1
Summary: An open-source framework for training large multimodal models
License: MIT
Keywords: machine learning
Classifier: Development Status :: 4 - Beta
Classifier: Intended Audience :: Developers
Classifier: Topic :: Scientific/Engineering :: Artificial Intelligence
Classifier: License :: OSI Approved :: MIT License
Classifier: Programming Language :: Python :: 3.9
License-File: LICENSE
Requires-Dist: einops
Requires-Dist: einops-exts
Requires-Dist: transformers >=4.28.1
Requires-Dist: torch ==2.0.1
Requires-Dist: pillow
Requires-Dist: open-clip-torch >=2.16.0
Requires-Dist: sentencepiece ==0.1.98
Provides-Extra: all
Requires-Dist: webdataset ; extra == 'all'
Requires-Dist: pillow ; extra == 'all'
Requires-Dist: nltk ; extra == 'all'
Requires-Dist: tqdm ; extra == 'all'
Requires-Dist: inflection ; extra == 'all'
Requires-Dist: pycocotools ; extra == 'all'
Requires-Dist: einops-exts ; extra == 'all'
Requires-Dist: wandb ; extra == 'all'
Requires-Dist: open-clip-torch >=2.16.0 ; extra == 'all'
Requires-Dist: torchvision ; extra == 'all'
Requires-Dist: transformers >=4.28.1 ; extra == 'all'
Requires-Dist: sentencepiece ==0.1.98 ; extra == 'all'
Requires-Dist: einops ; extra == 'all'
Requires-Dist: pycocoevalcap ; extra == 'all'
Requires-Dist: torch ==2.0.1 ; extra == 'all'
Requires-Dist: braceexpand ; extra == 'all'
Requires-Dist: scipy ; extra == 'all'
Provides-Extra: eval
Requires-Dist: scipy ; extra == 'eval'
Requires-Dist: torchvision ; extra == 'eval'
Requires-Dist: nltk ; extra == 'eval'
Requires-Dist: inflection ; extra == 'eval'
Requires-Dist: pycocoevalcap ; extra == 'eval'
Requires-Dist: pycocotools ; extra == 'eval'
Requires-Dist: tqdm ; extra == 'eval'
Provides-Extra: training
Requires-Dist: wandb ; extra == 'training'
Requires-Dist: torchvision ; extra == 'training'
Requires-Dist: braceexpand ; extra == 'training'
Requires-Dist: webdataset ; extra == 'training'
Requires-Dist: tqdm ; extra == 'training'
